ExceptNotifier/__init__.py
ExceptNotifier/base/__init__.py
ExceptNotifier/base/bard_receiver.py
ExceptNotifier/base/beep_sender.py
ExceptNotifier/base/chime_sender.py
ExceptNotifier/base/desktop_sender.py
ExceptNotifier/base/discord_sender.py
ExceptNotifier/base/kakao_sender.py
ExceptNotifier/base/line_sender.py
ExceptNotifier/base/mail_sender.py
ExceptNotifier/base/openai_receiver.py
ExceptNotifier/base/slack_sender.py
ExceptNotifier/base/sms_sender.py
ExceptNotifier/base/teams_sender.py
ExceptNotifier/base/telegram_sender.py
ExceptNotifier/base/wechat_sender.py
ExceptNotifier/base/whatsapp_sender.py
ExceptNotifier/ipycore/__init__.py
ExceptNotifier/ipycore/beep_notifier_ipython.py
ExceptNotifier/ipycore/chime_notifier_ipython.py
ExceptNotifier/ipycore/desktop_notifier_ipython.py
ExceptNotifier/ipycore/discord_notifier_ipython.py
ExceptNotifier/ipycore/kakao_notifier_ipython.py
ExceptNotifier/ipycore/line_notifier_ipython.py
ExceptNotifier/ipycore/mail_notifier_ipython.py
ExceptNotifier/ipycore/slack_notifier_ipython.py
ExceptNotifier/ipycore/sms_notifier_ipython.py
ExceptNotifier/ipycore/teams_notifier_ipython.py
ExceptNotifier/ipycore/telegram_notifier_ipython.py
ExceptNotifier/ipycore/wechat_notifier_ipython.py
ExceptNotifier/pycore/__init__.py
ExceptNotifier/pycore/beep_notifier.py
ExceptNotifier/pycore/chime_notifier.py
ExceptNotifier/pycore/desktop_notifier.py
ExceptNotifier/pycore/discord_notifier.py
ExceptNotifier/pycore/kakao_notifier.py
ExceptNotifier/pycore/line_notifier.py
ExceptNotifier/pycore/mail_notifier.py
ExceptNotifier/pycore/slack_notifier.py
ExceptNotifier/pycore/sms_notifier.py
ExceptNotifier/pycore/teams_notifier.py
ExceptNotifier/pycore/telegram_notifier.py
ExceptNotifier/pycore/wechat_notifier.py
ExceptNotifier/utils/__init__.py
ExceptNotifier/utils/kakao_token.py
exceptnotifier-0.2.11.dist-info/LICENSE
exceptnotifier-0.2.11.dist-info/METADATA
exceptnotifier-0.2.11.dist-info/WHEEL
exceptnotifier-0.2.11.dist-info/entry_points.txt
exceptnotifier-0.2.11.dist-info/top_level.txt
exceptnotifier-0.2.11.dist-info/RECORD
