Metadata-Version: 2.1
Name: exceptnotifier
Version: 0.2.11
Summary: With Python's try-except to receive notifications about Errors or Successes in your code through messenger app or email.
Home-page: https://github.com/dsdanielpark/ExceptNotifier
Author: daniel park
Author-email: parkminwoo1991@gmail.com
Keywords: Exception,Python,Python Exception Alarm,Error notifications,Customizable notifications,Traceback management,Single line alarm
Classifier: Development Status :: 3 - Alpha
Classifier: Intended Audience :: Science/Research
Classifier: Natural Language :: English
Classifier: Programming Language :: Python
Classifier: Programming Language :: Python :: 3.6
Classifier: Programming Language :: Python :: 3.7
Classifier: Programming Language :: Python :: 3.8
Classifier: License :: OSI Approved :: MIT License
Classifier: Programming Language :: Python :: 3.6
Classifier: Topic :: Scientific/Engineering :: Artificial Intelligence
Requires-Python: >=3.6
License-File: LICENSE
Requires-Dist: twilio
Requires-Dist: plyer
Requires-Dist: openai
Requires-Dist: discord
Requires-Dist: sphinx-rtd-theme
Requires-Dist: Sphinx
Requires-Dist: bardapi
